[
  {
    "word": "챙",
    "translation": "малгайн хамгаалалт",
    "hanja": "챙",
    "pos": "명사",
    "cefr": "B1"
  },
  {
    "word": "챙그랑",
    "translation": "шажигнах дуу",
    "hanja": null,
    "pos": "adverb",
    "cefr": "B2"
  },
  {
    "word": "챙기다",
    "translation": "бэлтгэх",
    "hanja": "챙기다",
    "pos": "verb",
    "cefr": "B1"
  },
  {
    "word": "챙챙",
    "translation": "чанг чанг (дуу)",
    "hanja": null,
    "pos": "부사",
    "cefr": "A2"
  },
  {
    "word": "챙피",
    "translation": "ичгүүр",
    "hanja": "챙피",
    "pos": "noun",
    "cefr": "B1"
  }
]