[
  {
    "word": "잣",
    "translation": "Нарсны самар",
    "hanja": "",
    "pos": "명사",
    "cefr": "B1"
  },
  {
    "word": "잣나무",
    "translation": "нарс мод",
    "hanja": null,
    "pos": "Noun",
    "cefr": "B2"
  },
  {
    "word": "잣다",
    "translation": "ээрэх",
    "hanja": null,
    "pos": "동사",
    "cefr": "B1"
  },
  {
    "word": "잣대",
    "translation": "хэмжүүр, стандарт",
    "hanja": null,
    "pos": "명사",
    "cefr": "B2"
  },
  {
    "word": "잣죽",
    "translation": "самрын будаа",
    "hanja": null,
    "pos": "명사",
    "cefr": "B1"
  }
]