[
  {
    "word": "찡",
    "translation": "түймэр тавьсан чимээ",
    "hanja": null,
    "pos": "부사",
    "cefr": "B2"
  },
  {
    "word": "찡그러지다",
    "translation": "мурийх",
    "hanja": null,
    "pos": "동사",
    "cefr": "B2"
  },
  {
    "word": "찡그리다",
    "translation": "Хөмсгөө зангидах, ундууцах",
    "hanja": null,
    "pos": "동사",
    "cefr": "B1"
  },
  {
    "word": "찡긋",
    "translation": "нүдээ анивчилах, хөмсгөө зангидах",
    "hanja": "찡긋",
    "pos": "부사",
    "cefr": "B1"
  },
  {
    "word": "찡긋거리다",
    "translation": "нүд ирмэх",
    "hanja": null,
    "pos": "verb",
    "cefr": "B1"
  },
  {
    "word": "찡긋찡긋",
    "translation": "байнга инээмсэглэх",
    "hanja": null,
    "pos": "부사",
    "cefr": "A2"
  },
  {
    "word": "찡긋하다",
    "translation": "Нүдээ анивчих",
    "hanja": "찡긋하다",
    "pos": "Verb",
    "cefr": "C1"
  },
  {
    "word": "찡기다",
    "translation": "хавчуулагдах (방언)",
    "hanja": "찡기다",
    "pos": "동사",
    "cefr": "C2"
  },
  {
    "word": "찡찡",
    "translation": "чанга чанга дуугарах (хүүхдийн уйлах дуу)",
    "hanja": null,
    "pos": "부사",
    "cefr": "A2"
  },
  {
    "word": "찡찡거리다",
    "translation": "уйлах, үглэх",
    "hanja": null,
    "pos": "ү.ү.",
    "cefr": "B1"
  },
  {
    "word": "찡찡대다",
    "translation": "уйлах, үглэх",
    "hanja": null,
    "pos": "동사",
    "cefr": "B2"
  },
  {
    "word": "찡하다",
    "translation": "зүрх шимшрэх",
    "hanja": "찡하다",
    "pos": "형용사",
    "cefr": "B2"
  }
]