[
  {
    "word": "톡",
    "translation": "цохих",
    "hanja": null,
    "pos": "부사",
    "cefr": "B1"
  },
  {
    "word": "톡소포자충",
    "translation": "токсоплазм",
    "hanja": "null",
    "pos": "명사",
    "cefr": "C1"
  },
  {
    "word": "톡소플라즈마",
    "translation": "токсоплазма",
    "hanja": "",
    "pos": "Noun",
    "cefr": "C2"
  },
  {
    "word": "톡신",
    "translation": "Токсин",
    "hanja": null,
    "pos": "명사",
    "cefr": "C1"
  },
  {
    "word": "톡톡",
    "translation": "тог тог",
    "hanja": "None",
    "pos": "Adverb",
    "cefr": "A2"
  },
  {
    "word": "톡톡거리다",
    "translation": "тас, тас хийх",
    "hanja": "",
    "pos": "동사",
    "cefr": "B2"
  },
  {
    "word": "톡톡하다",
    "translation": "зузаан",
    "hanja": null,
    "pos": "형용사",
    "cefr": "B2"
  },
  {
    "word": "톡톡히",
    "translation": "үр дүнтэй, үнэнээрээ",
    "hanja": null,
    "pos": "부사",
    "cefr": "B2"
  }
]